README.rst
setup.py
j1m/__init__.py
j1m/sphinxautointerface.py
j1m.sphinxautointerface.egg-info/PKG-INFO
j1m.sphinxautointerface.egg-info/SOURCES.txt
j1m.sphinxautointerface.egg-info/dependency_links.txt
j1m.sphinxautointerface.egg-info/namespace_packages.txt
j1m.sphinxautointerface.egg-info/requires.txt
j1m.sphinxautointerface.egg-info/top_level.txt