Metadata-Version: 1.1
Name: j1m.sphinxautointerface
Version: 0.3.0
Summary: Sphinx extension for documenting zope.interface interfaces
Home-page: http://bitbucket.org/j1m/sphinxautointerface
Author: Michael McNeil Forbes and Jim Fultom
Author-email: jim@jimfulton.info
License: BSD
Platform: any
Classifier: Development Status :: 4 - Beta
Classifier: Environment :: Console
Classifier: Environment :: Web Environment
Classifier: Intended Audience :: Developers
Classifier: License :: OSI Approved :: BSD License
Classifier: Operating System :: OS Independent
Classifier: Programming Language :: Python
Classifier: Framework :: Zope3
Classifier: Topic :: Documentation
Classifier: Topic :: Utilities
